noxnet/__init__.py
noxnet/_activation.py
noxnet/_attention.py
noxnet/_combine.py
noxnet/_linear.py
noxnet/_norm.py
noxnet/_typecheck.py
noxnet/_utils.py
noxnet-0.1.0.dist-info/METADATA
noxnet-0.1.0.dist-info/WHEEL
noxnet-0.1.0.dist-info/top_level.txt
noxnet-0.1.0.dist-info/RECORD
